hyped/serve/__init__.py
hyped/serve/__version__.py
hyped/serve/api.py
hyped/serve/router.py
hyped_serve-0.1.0.dist-info/LICENSE
hyped_serve-0.1.0.dist-info/METADATA
hyped_serve-0.1.0.dist-info/WHEEL
hyped_serve-0.1.0.dist-info/top_level.txt
hyped_serve-0.1.0.dist-info/RECORD
