Metadata-Version: 2.1
Name: hyped-serve
Version: 0.1.0
Summary: TODO
Author: open-hyped
License: Apache 2.0
Classifier: License :: Freely Distributable
Classifier: License :: OSI Approved :: Apache Software License
Classifier: Programming Language :: Python :: 3.11
Requires-Python: >=3.10
License-File: LICENSE
Requires-Dist: hyped
Requires-Dist: fastapi >=0.110.2
Requires-Dist: uvicorn[standard] >=0.29.0
Provides-Extra: linting
Requires-Dist: pre-commit ; extra == 'linting'
Provides-Extra: tests
Requires-Dist: pytest ; extra == 'tests'
Requires-Dist: pytest-cov ; extra == 'tests'
Requires-Dist: httpx ; extra == 'tests'
